httprobe/__init__.py
httprobe/main.py
httprobe-0.0.6.dist-info/LICENSE.md
httprobe-0.0.6.dist-info/METADATA
httprobe-0.0.6.dist-info/WHEEL
httprobe-0.0.6.dist-info/entry_points.txt
httprobe-0.0.6.dist-info/top_level.txt
httprobe-0.0.6.dist-info/RECORD
