Metadata-Version: 2.1
Name: httprobe
Version: 0.0.6
Summary: Probes a list of targets and returns details about responses
Home-page: https://github.com/midnight-repo/httprobe
Author: midnight_repo
Author-email: midnight_repo@protonmail.com
License: GPL-3.0
Platform: UNKNOWN
License-File: LICENSE.md
Requires-Dist: requests
Requires-Dist: pandas
Requires-Dist: tabulate
